Metadata-Version: 1.1
Name: RTCDataTypeAdaptor
Version: 0.1.0
Summary: DataTypeAdaptor codes and solution generator
Home-page: http://www.sugarsweetrobotics.com/
Author: ysuga
Author-email: ysuga@ysuga.net
License: GPLv3
Download-URL: https://github.com/sugarsweetrobotics/RTCDataTypeAdaptor
Platform: UNKNOWN
Classifier: Development Status :: 5 - Production/Stable
Classifier: Environment :: Console
Classifier: Intended Audience :: Developers
Classifier: License :: OSI Approved :: GNU General Public License v3 (GPLv3)
Classifier: Natural Language :: English
Classifier: Operating System :: OS Independent
Classifier: Programming Language :: Python
Classifier: Topic :: Scientific/Engineering
